{
  "timestamp": "2026-03-01T16:55:31",
  "sourceFiles": ["jdk/src/java.base/share/classes/java/util/FormatterBuilder.java"],
  "phaseTimings": {
    "totalMs": 1801.1,
    "compilationMs": 0.0,
    "irLoadingMs": 52.6,
    "callGraphMs": 1494.4,
    "dataflowTotalMs": 200.0,
    "sideEffectTotalMs": 0.7,
    "overheadMs": 53.5
  },
  "methods": [
    {
      "signature": "<java.util.FormatterBuilder: boolean isGenericDFS(java.text.DecimalFormatSymbols)>",
      "verdict": "SIDE_EFFECT_FREE",
      "reason": null,
      "dataflowMs": 9.6,
      "sideEffectMs": 0.0,
      "totalMs": 9.7,
      "jimpleStmtCount": 13,
      "graphNodes": 1,
      "graphEdges": 0
    },
    {
      "signature": "<java.util.FormatterBuilder: boolean validFlags(int,int)>",
      "verdict": "SIDE_EFFECT_FREE",
      "reason": null,
      "dataflowMs": 0.1,
      "sideEffectMs": 0.0,
      "totalMs": 0.1,
      "jimpleStmtCount": 9,
      "graphNodes": 0,
      "graphEdges": 0
    },
    {
      "signature": "<java.util.FormatterBuilder: int groupSize(java.util.Locale,java.text.DecimalFormatSymbols)>",
      "verdict": "SIDE_EFFECTING",
      "reason": "Locale parameter escapes to global scope",
      "dataflowMs": 36.1,
      "sideEffectMs": 0.0,
      "totalMs": 36.1,
      "jimpleStmtCount": 26,
      "graphNodes": 5,
      "graphEdges": 0
    },
    {
      "signature": "<java.util.FormatterBuilder: boolean isFlag(int,int)>",
      "verdict": "SIDE_EFFECT_FREE",
      "reason": null,
      "dataflowMs": 0.1,
      "sideEffectMs": 0.0,
      "totalMs": 0.1,
      "jimpleStmtCount": 8,
      "graphNodes": 0,
      "graphEdges": 0
    },
    {
      "signature": "<java.util.FormatterBuilder: java.lang.invoke.MethodHandle formatSpecifier(java.util.Formatter$FormatSpecifier,java.lang.Class)>",
      "verdict": "SIDE_EFFECTING",
      "reason": "Class parameter escapes to global scope",
      "dataflowMs": 22.1,
      "sideEffectMs": 0.0,
      "totalMs": 22.1,
      "jimpleStmtCount": 248,
      "graphNodes": 25,
      "graphEdges": 22
    },
    {
      "signature": "<java.util.FormatterBuilder: java.lang.invoke.MethodHandle buildFilters(java.util.List,java.util.List,java.lang.invoke.MethodHandle[])>",
      "verdict": "SIDE_EFFECTING",
      "reason": "writes to static field value",
      "dataflowMs": 21.1,
      "sideEffectMs": 0.0,
      "totalMs": 21.1,
      "jimpleStmtCount": 61,
      "graphNodes": 38,
      "graphEdges": 35
    },
    {
      "signature": "<java.util.FormatterBuilder: void <init>(java.lang.String,java.util.Locale,java.lang.Class[])>",
      "verdict": "SIDE_EFFECTING",
      "reason": "Locale parameter escapes to global scope",
      "dataflowMs": 9.9,
      "sideEffectMs": 0.0,
      "totalMs": 10.0,
      "jimpleStmtCount": 14,
      "graphNodes": 11,
      "graphEdges": 7
    },
    {
      "signature": "<java.util.FormatterBuilder: java.lang.Class mapType(java.lang.Class)>",
      "verdict": "SIDE_EFFECTING",
      "reason": "Class parameter escapes to global scope",
      "dataflowMs": 0.1,
      "sideEffectMs": 0.0,
      "totalMs": 0.1,
      "jimpleStmtCount": 8,
      "graphNodes": 1,
      "graphEdges": 0
    },
    {
      "signature": "<java.util.FormatterBuilder: java.lang.invoke.MethodHandle findStaticMethod(java.lang.Class,java.lang.String,java.lang.Class,java.lang.Class[])>",
      "verdict": "SIDE_EFFECTING",
      "reason": "Class parameter escapes to global scope",
      "dataflowMs": 8.2,
      "sideEffectMs": 0.0,
      "totalMs": 8.2,
      "jimpleStmtCount": 22,
      "graphNodes": 26,
      "graphEdges": 20
    },
    {
      "signature": "<java.util.FormatterBuilder: java.lang.invoke.MethodHandle findStringConcatItemConstructor(java.lang.Class,java.lang.Class[])>",
      "verdict": "SIDE_EFFECTING",
      "reason": "writes to static field simpleName",
      "dataflowMs": 18.9,
      "sideEffectMs": 0.0,
      "totalMs": 18.9,
      "jimpleStmtCount": 22,
      "graphNodes": 26,
      "graphEdges": 29
    },
    {
      "signature": "<java.util.FormatterBuilder: void <clinit>()>",
      "verdict": "SIDE_EFFECTING",
      "reason": "writes to static field FINull_MH",
      "dataflowMs": 11.7,
      "sideEffectMs": 0.4,
      "totalMs": 12.0,
      "jimpleStmtCount": 106,
      "graphNodes": 381,
      "graphEdges": 427
    },
    {
      "signature": "<java.util.FormatterBuilder: boolean nullCheck(java.lang.Object)>",
      "verdict": "SIDE_EFFECT_FREE",
      "reason": null,
      "dataflowMs": 0.1,
      "sideEffectMs": 0.0,
      "totalMs": 0.1,
      "jimpleStmtCount": 6,
      "graphNodes": 1,
      "graphEdges": 0
    },
    {
      "signature": "<java.util.FormatterBuilder: long toLong(int)>",
      "verdict": "SIDE_EFFECT_FREE",
      "reason": null,
      "dataflowMs": 0.0,
      "sideEffectMs": 0.0,
      "totalMs": 0.0,
      "jimpleStmtCount": 4,
      "graphNodes": 0,
      "graphEdges": 0
    },
    {
      "signature": "<java.util.FormatterBuilder: java.lang.invoke.MethodHandle build()>",
      "verdict": "SIDE_EFFECTING",
      "reason": "writes to static field value",
      "dataflowMs": 11.4,
      "sideEffectMs": 0.0,
      "totalMs": 11.5,
      "jimpleStmtCount": 34,
      "graphNodes": 51,
      "graphEdges": 51
    },
    {
      "signature": "<java.util.FormatterBuilder: java.lang.invoke.MethodHandle findMethod(java.lang.Class,java.lang.String,java.lang.Class,java.lang.Class[])>",
      "verdict": "SIDE_EFFECTING",
      "reason": "Class parameter escapes to global scope",
      "dataflowMs": 50.5,
      "sideEffectMs": 0.0,
      "totalMs": 50.5,
      "jimpleStmtCount": 22,
      "graphNodes": 26,
      "graphEdges": 20
    },
    {
      "signature": "<java.util.FormatterBuilder: boolean formattableCheck(java.lang.Object)>",
      "verdict": "SIDE_EFFECT_FREE",
      "reason": null,
      "dataflowMs": 0.2,
      "sideEffectMs": 0.0,
      "totalMs": 0.2,
      "jimpleStmtCount": 5,
      "graphNodes": 2,
      "graphEdges": 0
    }
  ],
  "statistics": {
    "methodCount": 16,
    "avgTimePerMethodMs": 12.5,
    "totalJimpleStmts": 608
  }
}
