{
  "timestamp": "2026-03-01T13:21:53",
  "sourceFiles": ["jdk/src/java.base/share/classes/java/util/OptionalLong.java"],
  "phaseTimings": {
    "totalMs": 7767.1,
    "compilationMs": 0.0,
    "irLoadingMs": 246.1,
    "callGraphMs": 6969.1,
    "dataflowTotalMs": 291.9,
    "sideEffectTotalMs": 1.2,
    "overheadMs": 258.8
  },
  "methods": [
    {
      "signature": "<java.util.OptionalLong: long orElseThrow()>",
      "verdict": "SIDE_EFFECT_FREE",
      "reason": null,
      "dataflowMs": 133.0,
      "sideEffectMs": 0.1,
      "totalMs": 133.1,
      "jimpleStmtCount": 8,
      "graphNodes": 6,
      "graphEdges": 7
    },
    {
      "signature": "<java.util.OptionalLong: boolean equals(java.lang.Object)>",
      "verdict": "SIDE_EFFECT_FREE",
      "reason": null,
      "dataflowMs": 1.1,
      "sideEffectMs": 0.0,
      "totalMs": 1.2,
      "jimpleStmtCount": 23,
      "graphNodes": 2,
      "graphEdges": 0
    },
    {
      "signature": "<java.util.OptionalLong: long orElse(long)>",
      "verdict": "SIDE_EFFECT_FREE",
      "reason": null,
      "dataflowMs": 0.4,
      "sideEffectMs": 0.0,
      "totalMs": 0.4,
      "jimpleStmtCount": 8,
      "graphNodes": 1,
      "graphEdges": 0
    },
    {
      "signature": "<java.util.OptionalLong: java.util.OptionalLong empty()>",
      "verdict": "SIDE_EFFECT_FREE",
      "reason": null,
      "dataflowMs": 0.3,
      "sideEffectMs": 0.0,
      "totalMs": 0.3,
      "jimpleStmtCount": 2,
      "graphNodes": 2,
      "graphEdges": 1
    },
    {
      "signature": "<java.util.OptionalLong: int hashCode()>",
      "verdict": "SIDE_EFFECT_FREE",
      "reason": null,
      "dataflowMs": 12.0,
      "sideEffectMs": 0.0,
      "totalMs": 12.0,
      "jimpleStmtCount": 8,
      "graphNodes": 1,
      "graphEdges": 0
    },
    {
      "signature": "<java.util.OptionalLong: boolean isPresent()>",
      "verdict": "SIDE_EFFECT_FREE",
      "reason": null,
      "dataflowMs": 0.3,
      "sideEffectMs": 0.0,
      "totalMs": 0.3,
      "jimpleStmtCount": 3,
      "graphNodes": 1,
      "graphEdges": 0
    },
    {
      "signature": "<java.util.OptionalLong: void <init>()>",
      "verdict": "SIDE_EFFECT_FREE",
      "reason": null,
      "dataflowMs": 0.4,
      "sideEffectMs": 0.1,
      "totalMs": 0.4,
      "jimpleStmtCount": 5,
      "graphNodes": 1,
      "graphEdges": 0
    },
    {
      "signature": "<java.util.OptionalLong: void <clinit>()>",
      "verdict": "SIDE_EFFECTING",
      "reason": "writes to static field EMPTY",
      "dataflowMs": 0.5,
      "sideEffectMs": 0.2,
      "totalMs": 0.7,
      "jimpleStmtCount": 4,
      "graphNodes": 2,
      "graphEdges": 0
    },
    {
      "signature": "<java.util.OptionalLong: void <init>(long)>",
      "verdict": "SIDE_EFFECT_FREE",
      "reason": null,
      "dataflowMs": 0.3,
      "sideEffectMs": 0.0,
      "totalMs": 0.3,
      "jimpleStmtCount": 6,
      "graphNodes": 1,
      "graphEdges": 0
    },
    {
      "signature": "<java.util.OptionalLong: java.util.OptionalLong of(long)>",
      "verdict": "SIDE_EFFECT_FREE",
      "reason": null,
      "dataflowMs": 0.5,
      "sideEffectMs": 0.0,
      "totalMs": 0.5,
      "jimpleStmtCount": 4,
      "graphNodes": 1,
      "graphEdges": 0
    },
    {
      "signature": "<java.util.OptionalLong: java.util.stream.LongStream stream()>",
      "verdict": "SIDE_EFFECT_FREE",
      "reason": null,
      "dataflowMs": 64.2,
      "sideEffectMs": 0.1,
      "totalMs": 64.3,
      "jimpleStmtCount": 8,
      "graphNodes": 5,
      "graphEdges": 5
    },
    {
      "signature": "<java.util.OptionalLong: void ifPresent(java.util.function.LongConsumer)>",
      "verdict": "SIDE_EFFECTING",
      "reason": "LongConsumer parameter escapes to global scope",
      "dataflowMs": 0.7,
      "sideEffectMs": 0.0,
      "totalMs": 0.8,
      "jimpleStmtCount": 7,
      "graphNodes": 2,
      "graphEdges": 0
    },
    {
      "signature": "<java.util.OptionalLong: long getAsLong()>",
      "verdict": "SIDE_EFFECT_FREE",
      "reason": null,
      "dataflowMs": 1.1,
      "sideEffectMs": 0.1,
      "totalMs": 1.1,
      "jimpleStmtCount": 8,
      "graphNodes": 6,
      "graphEdges": 7
    },
    {
      "signature": "<java.util.OptionalLong: long orElseGet(java.util.function.LongSupplier)>",
      "verdict": "SIDE_EFFECT_FREE",
      "reason": null,
      "dataflowMs": 2.2,
      "sideEffectMs": 0.1,
      "totalMs": 2.3,
      "jimpleStmtCount": 8,
      "graphNodes": 7,
      "graphEdges": 7
    },
    {
      "signature": "<java.util.OptionalLong: boolean isEmpty()>",
      "verdict": "SIDE_EFFECT_FREE",
      "reason": null,
      "dataflowMs": 0.4,
      "sideEffectMs": 0.0,
      "totalMs": 0.5,
      "jimpleStmtCount": 7,
      "graphNodes": 1,
      "graphEdges": 0
    },
    {
      "signature": "<java.util.OptionalLong: java.lang.String toString()>",
      "verdict": "SIDE_EFFECTING",
      "reason": "writes to static field count",
      "dataflowMs": 72.8,
      "sideEffectMs": 0.1,
      "totalMs": 72.9,
      "jimpleStmtCount": 13,
      "graphNodes": 19,
      "graphEdges": 21
    },
    {
      "signature": "<java.util.OptionalLong: void ifPresentOrElse(java.util.function.LongConsumer,java.lang.Runnable)>",
      "verdict": "SIDE_EFFECTING",
      "reason": "LongConsumer parameter escapes to global scope",
      "dataflowMs": 0.8,
      "sideEffectMs": 0.0,
      "totalMs": 0.8,
      "jimpleStmtCount": 10,
      "graphNodes": 3,
      "graphEdges": 0
    },
    {
      "signature": "<java.util.OptionalLong: long orElseThrow(java.util.function.Supplier)>",
      "verdict": "SIDE_EFFECTING",
      "reason": "Supplier parameter escapes to global scope",
      "dataflowMs": 1.0,
      "sideEffectMs": 0.1,
      "totalMs": 1.2,
      "jimpleStmtCount": 9,
      "graphNodes": 3,
      "graphEdges": 0
    }
  ],
  "statistics": {
    "methodCount": 18,
    "avgTimePerMethodMs": 16.3,
    "totalJimpleStmts": 141
  }
}
