{
  "timestamp": "2026-02-26T14:54:07",
  "sourceFiles": ["jdk/src/java.base/share/classes/java/util/Stack.java"],
  "phaseTimings": {
    "totalMs": 1914.8,
    "compilationMs": 0.0,
    "irLoadingMs": 55.3,
    "callGraphMs": 1787.6,
    "dataflowTotalMs": 12.4,
    "sideEffectTotalMs": 1.2,
    "overheadMs": 58.4
  },
  "methods": [
    {
      "signature": "<java.util.Stack: java.lang.Object push(java.lang.Object)>",
      "verdict": "SIDE_EFFECTING",
      "reason": "this escapes to global scope",
      "dataflowMs": 8.1,
      "sideEffectMs": 1.1,
      "totalMs": 9.2,
      "jimpleStmtCount": 4,
      "graphNodes": 2,
      "graphEdges": 0
    },
    {
      "signature": "<java.util.Stack: void <init>()>",
      "verdict": "SIDE_EFFECT_FREE",
      "reason": null,
      "dataflowMs": 0.2,
      "sideEffectMs": 0.0,
      "totalMs": 0.2,
      "jimpleStmtCount": 3,
      "graphNodes": 1,
      "graphEdges": 0
    },
    {
      "signature": "<java.util.Stack: java.lang.Object peek()>",
      "verdict": "SIDE_EFFECTING",
      "reason": "this escapes to global scope",
      "dataflowMs": 3.1,
      "sideEffectMs": 0.0,
      "totalMs": 3.1,
      "jimpleStmtCount": 9,
      "graphNodes": 3,
      "graphEdges": 0
    },
    {
      "signature": "<java.util.Stack: java.lang.Object pop()>",
      "verdict": "SIDE_EFFECTING",
      "reason": "this escapes to global scope",
      "dataflowMs": 0.5,
      "sideEffectMs": 0.0,
      "totalMs": 0.5,
      "jimpleStmtCount": 6,
      "graphNodes": 2,
      "graphEdges": 0
    },
    {
      "signature": "<java.util.Stack: int search(java.lang.Object)>",
      "verdict": "SIDE_EFFECTING",
      "reason": "this escapes to global scope",
      "dataflowMs": 0.2,
      "sideEffectMs": 0.0,
      "totalMs": 0.3,
      "jimpleStmtCount": 8,
      "graphNodes": 2,
      "graphEdges": 0
    },
    {
      "signature": "<java.util.Stack: boolean empty()>",
      "verdict": "SIDE_EFFECTING",
      "reason": "this escapes to global scope",
      "dataflowMs": 0.3,
      "sideEffectMs": 0.0,
      "totalMs": 0.3,
      "jimpleStmtCount": 7,
      "graphNodes": 1,
      "graphEdges": 0
    }
  ],
  "statistics": {
    "methodCount": 6,
    "avgTimePerMethodMs": 2.3,
    "totalJimpleStmts": 37
  }
}
