{
  "timestamp": "2026-02-23T21:25:22",
  "sourceFiles": ["jdk/src/java.base/share/classes/java/util/TimSort.java"],
  "phaseTimings": {
    "totalMs": 4166.9,
    "compilationMs": 0.0,
    "irLoadingMs": 145.3,
    "callGraphMs": 3805.5,
    "dataflowTotalMs": 168.9,
    "sideEffectTotalMs": 3.1,
    "overheadMs": 44.1
  },
  "methods": [
    {
      "signature": "<java.util.TimSort: int gallopLeft(java.lang.Object,java.lang.Object[],int,int,int,java.util.Comparator)>",
      "verdict": "SIDE_EFFECTING",
      "reason": "Object parameter escapes to global scope",
      "dataflowMs": 21.7,
      "sideEffectMs": 2.1,
      "totalMs": 23.8,
      "jimpleStmtCount": 83,
      "graphNodes": 7,
      "graphEdges": 0
    },
    {
      "signature": "<java.util.TimSort: int gallopRight(java.lang.Object,java.lang.Object[],int,int,int,java.util.Comparator)>",
      "verdict": "SIDE_EFFECTING",
      "reason": "Object parameter escapes to global scope",
      "dataflowMs": 3.3,
      "sideEffectMs": 0.0,
      "totalMs": 3.4,
      "jimpleStmtCount": 83,
      "graphNodes": 7,
      "graphEdges": 0
    },
    {
      "signature": "<java.util.TimSort: java.lang.Object[] ensureCapacity(int)>",
      "verdict": "SIDE_EFFECTING",
      "reason": "mutates this via field tmp",
      "dataflowMs": 14.1,
      "sideEffectMs": 0.2,
      "totalMs": 14.4,
      "jimpleStmtCount": 24,
      "graphNodes": 5,
      "graphEdges": 3
    },
    {
      "signature": "<java.util.TimSort: void mergeLo(int,int,int,int)>",
      "verdict": "SIDE_EFFECTING",
      "reason": "mutates this via field minGallop",
      "dataflowMs": 16.9,
      "sideEffectMs": 0.1,
      "totalMs": 17.0,
      "jimpleStmtCount": 167,
      "graphNodes": 30,
      "graphEdges": 5
    },
    {
      "signature": "<java.util.TimSort: void mergeHi(int,int,int,int)>",
      "verdict": "SIDE_EFFECTING",
      "reason": "mutates this via field minGallop",
      "dataflowMs": 7.5,
      "sideEffectMs": 0.1,
      "totalMs": 7.6,
      "jimpleStmtCount": 189,
      "graphNodes": 30,
      "graphEdges": 5
    },
    {
      "signature": "<java.util.TimSort: void mergeAt(int)>",
      "verdict": "SIDE_EFFECTING",
      "reason": "mutates this via field minGallop",
      "dataflowMs": 3.4,
      "sideEffectMs": 0.1,
      "totalMs": 3.5,
      "jimpleStmtCount": 107,
      "graphNodes": 38,
      "graphEdges": 9
    },
    {
      "signature": "<java.util.TimSort: void mergeCollapse()>",
      "verdict": "SIDE_EFFECTING",
      "reason": "mutates this via field minGallop",
      "dataflowMs": 92.2,
      "sideEffectMs": 0.1,
      "totalMs": 92.3,
      "jimpleStmtCount": 47,
      "graphNodes": 39,
      "graphEdges": 10
    },
    {
      "signature": "<java.util.TimSort: void reverseRange(java.lang.Object[],int,int)>",
      "verdict": "SIDE_EFFECTING",
      "reason": "mutates Object[] parameter via field array element",
      "dataflowMs": 0.2,
      "sideEffectMs": 0.0,
      "totalMs": 0.3,
      "jimpleStmtCount": 15,
      "graphNodes": 3,
      "graphEdges": 0
    },
    {
      "signature": "<java.util.TimSort: int countRunAndMakeAscending(java.lang.Object[],int,int,java.util.Comparator)>",
      "verdict": "SIDE_EFFECTING",
      "reason": "mutates Object[] parameter via field array element",
      "dataflowMs": 0.8,
      "sideEffectMs": 0.0,
      "totalMs": 0.8,
      "jimpleStmtCount": 38,
      "graphNodes": 7,
      "graphEdges": 0
    },
    {
      "signature": "<java.util.TimSort: void <init>(java.lang.Object[],java.util.Comparator,java.lang.Object[],int,int)>",
      "verdict": "SIDE_EFFECT_FREE",
      "reason": null,
      "dataflowMs": 0.6,
      "sideEffectMs": 0.0,
      "totalMs": 0.6,
      "jimpleStmtCount": 47,
      "graphNodes": 8,
      "graphEdges": 6
    },
    {
      "signature": "<java.util.TimSort: void pushRun(int,int)>",
      "verdict": "SIDE_EFFECTING",
      "reason": "mutates this via field stackSize",
      "dataflowMs": 0.1,
      "sideEffectMs": 0.0,
      "totalMs": 0.1,
      "jimpleStmtCount": 13,
      "graphNodes": 3,
      "graphEdges": 2
    },
    {
      "signature": "<java.util.TimSort: void binarySort(java.lang.Object[],int,int,int,java.util.Comparator)>",
      "verdict": "SIDE_EFFECTING",
      "reason": "Object[] parameter escapes to global scope",
      "dataflowMs": 0.9,
      "sideEffectMs": 0.0,
      "totalMs": 0.9,
      "jimpleStmtCount": 56,
      "graphNodes": 6,
      "graphEdges": 0
    },
    {
      "signature": "<java.util.TimSort: void mergeForceCollapse()>",
      "verdict": "SIDE_EFFECTING",
      "reason": "mutates this via field minGallop",
      "dataflowMs": 2.6,
      "sideEffectMs": 0.1,
      "totalMs": 2.7,
      "jimpleStmtCount": 17,
      "graphNodes": 39,
      "graphEdges": 10
    },
    {
      "signature": "<java.util.TimSort: int minRunLength(int)>",
      "verdict": "SIDE_EFFECT_FREE",
      "reason": null,
      "dataflowMs": 0.2,
      "sideEffectMs": 0.0,
      "totalMs": 0.2,
      "jimpleStmtCount": 15,
      "graphNodes": 1,
      "graphEdges": 0
    },
    {
      "signature": "<java.util.TimSort: void sort(java.lang.Object[],int,int,java.util.Comparator,java.lang.Object[],int,int)>",
      "verdict": "SIDE_EFFECTING",
      "reason": "Object[] parameter escapes to global scope",
      "dataflowMs": 4.0,
      "sideEffectMs": 0.1,
      "totalMs": 4.1,
      "jimpleStmtCount": 60,
      "graphNodes": 82,
      "graphEdges": 6
    },
    {
      "signature": "<java.util.TimSort: void <clinit>()>",
      "verdict": "SIDE_EFFECTING",
      "reason": "writes to static field $assertionsDisabled",
      "dataflowMs": 0.1,
      "sideEffectMs": 0.1,
      "totalMs": 0.2,
      "jimpleStmtCount": 8,
      "graphNodes": 1,
      "graphEdges": 0
    }
  ],
  "statistics": {
    "methodCount": 16,
    "avgTimePerMethodMs": 10.7,
    "totalJimpleStmts": 969
  }
}
